jrai_common_mixins/__init__.py
jrai_common_mixins/cachable.py
jrai_common_mixins/registrable.py
jrai_common_mixins/version.py
jrai_common_mixins-2025.6.dist-info/METADATA
jrai_common_mixins-2025.6.dist-info/WHEEL
jrai_common_mixins-2025.6.dist-info/licenses/LICENSE.txt
jrai_common_mixins-2025.6.dist-info/RECORD
