Metadata-Version: 2.4
Name: jrai-common_mixins
Version: 2025.6
Summary: A collection of recurring mixin classes.
Project-URL: Homepage, https://gitlab.inria.fr/jrye/jrai-common_mixins
Project-URL: Source, https://gitlab.inria.fr/jrye/jrai-common_mixins.git
Project-URL: Documentation, https://jrye.gitlabpages.inria.fr/jrai-common_mixins
Project-URL: Issues, https://gitlab.inria.fr/jrye/jrai-common_mixins/issues
Author-email: Jan-Michael Rye <jan-michael.rye@inria.fr>
License: MIT License
License-File: LICENSE.txt
Classifier: License :: OSI Approved :: MIT License
Classifier: Operating System :: OS Independent
Classifier: Programming Language :: Python :: 3
Requires-Python: >=3.8
Provides-Extra: test
Requires-Dist: coverage; extra == 'test'
Requires-Dist: freezegun; extra == 'test'
